docs/__init__.py
docs/conf.py
docs/settings.py
mmpy_bot/__init__.py
mmpy_bot/bot.py
mmpy_bot/driver.py
mmpy_bot/event_handler.py
mmpy_bot/function.py
mmpy_bot/scheduler.py
mmpy_bot/settings.py
mmpy_bot/threadpool.py
mmpy_bot/utils.py
mmpy_bot/version.txt
mmpy_bot/webhook_server.py
mmpy_bot/wrappers.py
mmpy_bot/plugins/__init__.py
mmpy_bot/plugins/base.py
mmpy_bot/plugins/example.py
mmpy_bot/plugins/help_example.py
mmpy_bot/plugins/webhook_example.py
mmpy_bot-2.2.1.dist-info/AUTHORS.rst
mmpy_bot-2.2.1.dist-info/LICENSE
mmpy_bot-2.2.1.dist-info/METADATA
mmpy_bot-2.2.1.dist-info/WHEEL
mmpy_bot-2.2.1.dist-info/entry_points.txt
mmpy_bot-2.2.1.dist-info/top_level.txt
mmpy_bot-2.2.1.dist-info/RECORD
