Metadata-Version: 2.2
Name: mmpy_bot
Version: 2.2.1
Summary: A python based bot for Mattermost with its own webhook server.
Home-page: https://github.com/attzonko/mmpy_bot
Author: Alex Tzonkov
Author-email: alex.tzonkov@gmail.com
License: MIT
Keywords: chat bot mattermost
Platform: Any
Classifier: Development Status :: 5 - Production/Stable
Classifier: License :: OSI Approved :: MIT License
Classifier: Intended Audience :: Developers
Classifier: Operating System :: OS Independent
Classifier: Programming Language :: Python :: 3.8
Classifier: Programming Language :: Python :: 3.9
Classifier: Programming Language :: Python :: 3.10
Classifier: Topic :: Internet :: WWW/HTTP
Classifier: Topic :: Software Development :: Libraries :: Python Modules
Requires-Python: >=3.8
License-File: LICENSE
License-File: AUTHORS.rst
Requires-Dist: httpx<0.28.0,>=0.27.0
Requires-Dist: aiohttp>=3.9.5
Requires-Dist: click>=8.1.7
Requires-Dist: mattermostautodriver>=2.0.0
Requires-Dist: schedule>=1.2.2
Provides-Extra: dev
Requires-Dist: black==24.4.2; extra == "dev"
Requires-Dist: docformatter==1.7.5; extra == "dev"
Requires-Dist: filelock==3.15.4; extra == "dev"
Requires-Dist: isort==5.13.2; extra == "dev"
Requires-Dist: flake8==7.1.0; extra == "dev"
Requires-Dist: pytest==8.2.2; extra == "dev"
Requires-Dist: pytest-xdist==3.6.1; extra == "dev"
Requires-Dist: pytype==2024.4.11; extra == "dev"
Requires-Dist: snapshottest==0.6.0; extra == "dev"
Dynamic: author
Dynamic: author-email
Dynamic: classifier
Dynamic: description
Dynamic: description-content-type
Dynamic: home-page
Dynamic: keywords
Dynamic: license
Dynamic: platform
Dynamic: provides-extra
Dynamic: requires-dist
Dynamic: requires-python
Dynamic: summary
